setup.py
docs/HISTORY.txt
wow/__init__.py
wow.armoryapi.egg-info/PKG-INFO
wow.armoryapi.egg-info/SOURCES.txt
wow.armoryapi.egg-info/dependency_links.txt
wow.armoryapi.egg-info/entry_points.txt
wow.armoryapi.egg-info/namespace_packages.txt
wow.armoryapi.egg-info/not-zip-safe
wow.armoryapi.egg-info/requires.txt
wow.armoryapi.egg-info/top_level.txt
wow/armoryapi/README.txt
wow/armoryapi/__init__.py
wow/armoryapi/armory_api.py
wow/armoryapi/test_armory.py