Metadata-Version: 1.0
Name: wow.armoryapi
Version: 0.8
Summary: Python World of Warcraft Armory API
Home-page: http://code.google.com/p/wowarmoryapi/
Author: Marc Goetz
Author-email: goetz.marc@googlemail.com
License: GPL
Keywords: armory api wow warcraft
Platform: UNKNOWN
Classifier: Programming Language :: Python
